iambus/__init__.py
iambus/base/__init__.py
iambus/base/dispatcher.py
iambus/base/maps.py
iambus/base/engine/__init__.py
iambus/base/engine/events.py
iambus/base/engine/requests.py
iambus/base/handlers/__init__.py
iambus/base/handlers/abstract.py
iambus/base/handlers/wrapper.py
iambus/base/routers/__init__.py
iambus/base/routers/eventrouter.py
iambus/base/routers/messagerouter.py
iambus/base/routers/requestrouter.py
iambus/core/__init__.py
iambus/core/exceptions.py
iambus/core/helpers.py
iambus/core/signals.py
iambus/core/types.py
iambus/core/api/__init__.py
iambus/core/api/dispatcher.py
iambus/core/api/engine.py
iambus/core/api/handlers.py
iambus/core/api/isolation.py
iambus/core/api/maps.py
iambus/core/api/other.py
iambus/core/api/routers.py
iambus/core/api/typedef.py
iambus/core/api/typing.py
iambus/core/dependency/__init__.py
iambus/core/dependency/providers.py
iambus/core/inspection/__init__.py
iambus/core/inspection/sig.py
iambus/core/inspection/utils.py
iambus-0.2.1.dist-info/METADATA
iambus-0.2.1.dist-info/WHEEL
iambus-0.2.1.dist-info/entry_points.txt
iambus-0.2.1.dist-info/licenses/MITLicense
iambus-0.2.1.dist-info/RECORD
