Metadata-Version: 2.4
Name: iambus
Version: 0.2.1
Summary: Async message bus framework designed for event-driven python monoliths or microservice nodes
Project-URL: Repository, https://github.com/andrei-samofalov/async-py-bus
Project-URL: Issues, https://github.com/andrei-samofalov/async-py-bus/issues
Author-email: Andrei Samofalov <andrei.e.samofalov@gmail.com>
Maintainer-email: Andrei Samofalov <andrei.e.samofalov@gmail.com>
License-File: MITLicense
Keywords: async,events,message bus,modular,monolith,python,queue
Classifier: Development Status :: 4 - Beta
Classifier: Framework :: AsyncIO
Classifier: Intended Audience :: Developers
Classifier: Intended Audience :: System Administrators
Classifier: Programming Language :: Python :: 3.10
Classifier: Programming Language :: Python :: 3.11
Classifier: Programming Language :: Python :: 3.12
Classifier: Programming Language :: Python :: 3.13
Classifier: Programming Language :: Python :: Implementation :: PyPy
Classifier: Topic :: Software Development
Classifier: Topic :: Software Development :: Libraries
Classifier: Topic :: Software Development :: Libraries :: Application Frameworks
Classifier: Typing :: Typed
Requires-Python: >=3.11
